pudu/__init__.py
pudu/error_handler.py
pudu/masks.py
pudu/perturbation.py
pudu/plots.py
pudu/pudu.py
pudu/standards.py
pudu-0.3.4.dist-info/LICENSE
pudu-0.3.4.dist-info/METADATA
pudu-0.3.4.dist-info/WHEEL
pudu-0.3.4.dist-info/dependency_links.txt
pudu-0.3.4.dist-info/top_level.txt
pudu-0.3.4.dist-info/RECORD
