Metadata-Version: 2.1
Name: pudu
Version: 0.3.4
Summary: A Python library for explainability of machine learinng algorithms in an agnostic, deterministic, and simple way.
Home-page: https://github.com/pudu-py/pudu
Author: pudu
Author-email: puduhola@gmail.com
License: MIT license
Keywords: pudu
Classifier: Development Status :: 2 - Pre-Alpha
Classifier: Intended Audience :: Developers
Classifier: License :: OSI Approved :: MIT License
Classifier: Natural Language :: English
Classifier: Programming Language :: Python :: 3
Classifier: Programming Language :: Python :: 3.7
Classifier: Programming Language :: Python :: 3.8
Classifier: Programming Language :: Python :: 3.9
Classifier: Programming Language :: Python :: 3.10
Requires-Python: >=3.7
License-File: LICENSE
Requires-Dist: numpy
Requires-Dist: pandas
Requires-Dist: matplotlib
Requires-Dist: spectrapepper
Requires-Dist: scikit-learn
Requires-Dist: tensorflow ==2.11
